.gitignore
MANIFEST.in
README.rst
setup.cfg
setup.py
docs/HISTORY.txt
docs/LICENSE.GPL
docs/LICENSE.txt
raptus/__init__.py
raptus.easyslider.egg-info/PKG-INFO
raptus.easyslider.egg-info/SOURCES.txt
raptus.easyslider.egg-info/dependency_links.txt
raptus.easyslider.egg-info/entry_points.txt
raptus.easyslider.egg-info/namespace_packages.txt
raptus.easyslider.egg-info/not-zip-safe
raptus.easyslider.egg-info/requires.txt
raptus.easyslider.egg-info/top_level.txt
raptus/easyslider/__init__.py
raptus/easyslider/configure.zcml
raptus/easyslider/browser/__init__.py
raptus/easyslider/browser/configure.zcml
raptus/easyslider/browser/easyslider.css
raptus/easyslider/browser/easyslider.init.js
raptus/easyslider/browser/easyslider.js
raptus/easyslider/browser/next.gif
raptus/easyslider/browser/prev.gif
raptus/easyslider/browser/vertical-next.gif
raptus/easyslider/browser/vertical-prev.gif
raptus/easyslider/profiles/default/cssregistry.xml
raptus/easyslider/profiles/default/jsregistry.xml
raptus/easyslider/profiles/default/metadata.xml
raptus/easyslider/profiles/default/propertiestool.xml
raptus/easyslider/profiles/default/skins.xml
raptus/easyslider/skins/raptus_easyslider/easyslider.settings.js.py