Metadata-Version: 1.1
Name: raptus.easyslider
Version: 1.0a4
Summary: Provides the easySlider jQuery plugin integrated into Plone
Home-page: https://github.com/Raptus/raptus.easyslider
Author: Raptus AG
Author-email: dev@raptus.com
License: GPL
Platform: UNKNOWN
Classifier: Programming Language :: Python
Classifier: Topic :: Software Development :: Libraries :: Python Modules
